LICENSE
MANIFEST.in
README.md
requirements.txt
setup.cfg
setup.py
vr_charcoal/__init__.py
vr_charcoal/vr_charcoal.py
vr_charcoal.egg-info/PKG-INFO
vr_charcoal.egg-info/SOURCES.txt
vr_charcoal.egg-info/dependency_links.txt
vr_charcoal.egg-info/not-zip-safe
vr_charcoal.egg-info/top_level.txt